dbiu_databases/__init__.py
dbiu_databases/base.db
dbiu_databases-18.dist-info/METADATA
dbiu_databases-18.dist-info/WHEEL
dbiu_databases-18.dist-info/top_level.txt
dbiu_databases-18.dist-info/RECORD
