Metadata-Version: 2.2
Name: dbiu_databases
Version: 18
Dynamic: description
Dynamic: description-content-type
